README.md
setup.py
sniplet/__init__.py
sniplet/__main__.py
sniplet/_helper.py
sniplet/_snipper.py
sniplet/sniplet.py
sniplet.egg-info/PKG-INFO
sniplet.egg-info/SOURCES.txt
sniplet.egg-info/dependency_links.txt
sniplet.egg-info/entry_points.txt
sniplet.egg-info/requires.txt
sniplet.egg-info/top_level.txt