Metadata-Version: 1.0
Name: sniplet
Version: 1.0.5
Summary: Python command line application for text replacement
Home-page: https://github.com/veera2508
Author: Veeraraghavan-Narasimhan
Author-email: virunarasimhan25@gmail.com
License: UNKNOWN
Platform: UNKNOWN
